flowrisk/__init__.py
flowrisk/measure.py
flowrisk/examples/__init__.py
flowrisk/examples/usstocks.py
flowrisk/examples/data/AAPL_2018_11_22.csv
flowrisk/examples/data/CBIO_2018_11_22.csv
flowrisk/examples/data/FBNC_2018_11_22.csv
flowrisk/examples/data/GNC_2018_11_22.csv
flowrisk/examples/data/GS_2018_11_22.csv
flowrisk/examples/data/INTC_2018_11_22.csv
flowrisk/examples/data/NDLS_2018_11_22.csv
flowrisk/examples/data/NVDA_2018_11_22.csv
flowrisk/examples/data/QES_2018_11_22.csv
flowrisk/examples/data/V_2018_11_22.csv
flowrisk/examples/data/__init__.py
flowrisk/tools/__init__.py
flowrisk/tools/band.py
flowrisk/tools/vol.py
flowrisk/toxicity/__init__.py
flowrisk/toxicity/bulk.py
flowrisk/toxicity/vpin.py
flowrisk-0.3.0.dist-info/METADATA
flowrisk-0.3.0.dist-info/WHEEL
flowrisk-0.3.0.dist-info/top_level.txt
flowrisk-0.3.0.dist-info/zip-safe
flowrisk-0.3.0.dist-info/RECORD
