Metadata-Version: 2.1
Name: flowrisk
Version: 0.3.0
Summary: Order flow risk measures in Python
Home-page: https://github.com/hanxixuana/flowrisk
Author: Xixuan Han
Author-email: xixuanhan@gmail.com
License: MIT
Platform: UNKNOWN
Classifier: Programming Language :: Python :: 3.8
Classifier: License :: OSI Approved :: MIT License
Classifier: Operating System :: OS Independent
Requires-Dist: numpy
Requires-Dist: pandas
Requires-Dist: matplotlib
Requires-Dist: scipy
